{
  "minecraft:recipes/decorations/crafting_table": {
    "criteria": {
      "unlock_right_away": "2023-08-24 23:41:00 +0400"
    },
    "done": true
  },
  "minecraft:adventure/adventuring_time": {
    "criteria": {
      "minecraft:snowy_plains": "2023-08-24 23:41:01 +0400",
      "minecraft:snowy_beach": "2023-08-25 01:39:55 +0400",
      "minecraft:meadow": "2023-08-25 01:40:22 +0400",
      "minecraft:plains": "2023-08-25 01:40:08 +0400"
    },
    "done": false
  },
  "minecraft:recipes/decorations/campfire": {
    "criteria": {
      "has_coal": "2023-08-25 01:41:18 +0400"
    },
    "done": true
  },
  "minecraft:recipes/building_blocks/coal_block": {
    "criteria": {
      "has_coal": "2023-08-25 01:41:18 +0400"
    },
    "done": true
  },
  "minecraft:story/root": {
    "criteria": {
      "crafting_table": "2023-08-25 01:41:30 +0400"
    },
    "done": true
  },
  "minecraft:recipes/decorations/chest": {
    "criteria": {
      "has_lots_of_items": "2023-08-25 01:42:10 +0400"
    },
    "done": true
  },
  "minecraft:recipes/decorations/torch": {
    "criteria": {
      "has_stone_pickaxe": "2023-08-25 01:47:18 +0400"
    },
    "done": true
  },
  "minecraft:recipes/tools/golden_axe": {
    "criteria": {
      "has_gold_ingot": "2023-08-25 01:50:44 +0400"
    },
    "done": true
  },
  "minecraft:recipes/tools/golden_pickaxe": {
    "criteria": {
      "has_gold_ingot": "2023-08-25 01:50:44 +0400"
    },
    "done": true
  },
  "minecraft:recipes/misc/gold_nugget": {
    "criteria": {
      "has_gold_ingot": "2023-08-25 01:50:44 +0400"
    },
    "done": true
  },
  "minecraft:recipes/tools/golden_shovel": {
    "criteria": {
      "has_gold_ingot": "2023-08-25 01:50:44 +0400"
    },
    "done": true
  },
  "minecraft:recipes/food/golden_apple": {
    "criteria": {
      "has_gold_ingot": "2023-08-25 01:50:44 +0400"
    },
    "done": true
  },
  "minecraft:story/upgrade_tools": {
    "criteria": {
      "stone_pickaxe": "2023-08-25 01:47:18 +0400"
    },
    "done": true
  },
  "minecraft:recipes/combat/golden_boots": {
    "criteria": {
      "has_gold_ingot": "2023-08-25 01:50:44 +0400"
    },
    "done": true
  },
  "minecraft:recipes/combat/golden_helmet": {
    "criteria": {
      "has_gold_ingot": "2023-08-25 01:50:44 +0400"
    },
    "done": true
  },
  "minecraft:recipes/combat/golden_sword": {
    "criteria": {
      "has_gold_ingot": "2023-08-25 01:50:44 +0400"
    },
    "done": true
  },
  "minecraft:recipes/building_blocks/gold_block": {
    "criteria": {
      "has_gold_ingot": "2023-08-25 01:50:44 +0400"
    },
    "done": true
  },
  "minecraft:recipes/combat/golden_chestplate": {
    "criteria": {
      "has_gold_ingot": "2023-08-25 01:50:44 +0400"
    },
    "done": true
  },
  "minecraft:recipes/tools/golden_hoe": {
    "criteria": {
      "has_gold_ingot": "2023-08-25 01:50:44 +0400"
    },
    "done": true
  },
  "minecraft:recipes/redstone/light_weighted_pressure_plate": {
    "criteria": {
      "has_gold_ingot": "2023-08-25 01:50:44 +0400"
    },
    "done": true
  },
  "minecraft:recipes/combat/golden_leggings": {
    "criteria": {
      "has_gold_ingot": "2023-08-25 01:50:44 +0400"
    },
    "done": true
  },
  "DataVersion": 3465
}